{"summary": {"level_counts": {"INFO": 41, "TRACE": 7}, "top_modules": {".....mailslot_create": 12, "....mailbox_register": 12, "...read_physical_netif": 8, "..entity_initialize": 6, "..reg_process": 3, ".main": 2, "..settcpimage": 2, "...locate_configFile": 1, "....mailslot_create": 1, "...mailbox_register": 1}}, "patterns": {"common_messages": {"mailbox allocated for rsvp-udp\r": 6, "creating mailslot for RSVP via UDP\r": 6, "mailbox allocated for rsvp\r": 6, "creating mailslot for RSVP\r": 6, "*************** RSVP Agent started ***************\r": 1}, "interface_messages": {"Get TCP images rc - EDC8112I Operation not supported on socket.\r": 1, "index #0, interface VLINK1 has address 129.1.1.1, ifidx 0\r": 1, "index #1, interface TR1 has address 9.37.65.139, ifidx 1\r": 1, "index #2, interface LINK11 has address 9.67.100.1, ifidx 2\r": 1, "index #3, interface LINK12 has address 9.67.101.1, ifidx 3\r": 1}}, "anomalies": {"unusual_time_gaps": {"8": 